spherical_harmonic_inversion/__init__.py
spherical_harmonic_inversion/inversion.py
spherical_harmonic_inversion/utils.py
tests/test_inversion.py
spherical_harmonic_inversion-0.1.0.dist-info/METADATA
spherical_harmonic_inversion-0.1.0.dist-info/WHEEL
spherical_harmonic_inversion-0.1.0.dist-info/top_level.txt
spherical_harmonic_inversion-0.1.0.dist-info/RECORD
