Metadata-Version: 2.4
Name: spherical-harmonic-inversion
Version: 0.1.0
Summary: Spherical harmonic inversion utilities for geophysics
Author-email: Issac Jacob <ij264@cam.ac.uk>
Requires-Dist: numpy
Requires-Dist: scipy
Requires-Dist: pandas
Requires-Dist: xarray
Requires-Dist: pygmt
Requires-Dist: pyshtools
